{"nodes": [{"id": "client_py", "label": "client.py", "file_type": "code", "source_file": "client.py", "source_location": "L1"}, {"id": "client_customerserviceenv", "label": "CustomerServiceEnv", "file_type": "code", "source_file": "client.py", "source_location": "L17"}, {"id": "client_customerserviceenv_step_payload", "label": "._step_payload()", "file_type": "code", "source_file": "client.py", "source_location": "L35"}, {"id": "client_customerserviceenv_parse_result", "label": "._parse_result()", "file_type": "code", "source_file": "client.py", "source_location": "L45"}, {"id": "client_customerserviceenv_parse_state", "label": "._parse_state()", "file_type": "code", "source_file": "client.py", "source_location": "L70"}, {"id": "client_rationale_20", "label": "Client for the Customer Service Agent Environment.      Example:         >>> wit", "file_type": "rationale", "source_file": "client.py", "source_location": "L20"}, {"id": "client_rationale_36", "label": "Convert action to JSON payload.", "file_type": "rationale", "source_file": "client.py", "source_location": "L36"}, {"id": "client_rationale_46", "label": "Parse server response into StepResult.", "file_type": "rationale", "source_file": "client.py", "source_location": "L46"}, {"id": "client_rationale_71", "label": "Parse server response into State object.", "file_type": "rationale", "source_file": "client.py", "source_location": "L71"}], "edges": [{"source": "client_py", "target": "typing", "relation": "imports_from", "confidence": "EXTRACTED", "source_file": "client.py", "source_location": "L9", "weight": 1.0}, {"source": "client_py", "target": "openenv_core", "relation": "imports_from", "confidence": "EXTRACTED", "source_file": "client.py", "source_location": "L11", "weight": 1.0}, {"source": "client_py", "target": "openenv_core_client_types", "relation": "imports_from", "confidence": "EXTRACTED", "source_file": "client.py", "source_location": "L12", "weight": 1.0}, {"source": "client_py", "target": "models", "relation": "imports_from", "confidence": "EXTRACTED", "source_file": "client.py", "source_location": "L14", "weight": 1.0}, {"source": "client_py", "target": "client_customerserviceenv", "relation": "contains", "confidence": "EXTRACTED", "source_file": "client.py", "source_location": "L17", "weight": 1.0}, {"source": "client_customerserviceenv", "target": "client_customerserviceenv_step_payload", "relation": "method", "confidence": "EXTRACTED", "source_file": "client.py", "source_location": "L35", "weight": 1.0}, {"source": "client_customerserviceenv", "target": "client_customerserviceenv_parse_result", "relation": "method", "confidence": "EXTRACTED", "source_file": "client.py", "source_location": "L45", "weight": 1.0}, {"source": "client_customerserviceenv", "target": "client_customerserviceenv_parse_state", "relation": "method", "confidence": "EXTRACTED", "source_file": "client.py", "source_location": "L70", "weight": 1.0}, {"source": "client_rationale_20", "target": "client_customerserviceenv", "relation": "rationale_for", "confidence": "EXTRACTED", "source_file": "client.py", "source_location": "L20", "weight": 1.0}, {"source": "client_rationale_36", "target": "client_customerserviceenv_step_payload", "relation": "rationale_for", "confidence": "EXTRACTED", "source_file": "client.py", "source_location": "L36", "weight": 1.0}, {"source": "client_rationale_46", "target": "client_customerserviceenv_parse_result", "relation": "rationale_for", "confidence": "EXTRACTED", "source_file": "client.py", "source_location": "L46", "weight": 1.0}, {"source": "client_rationale_71", "target": "client_customerserviceenv_parse_state", "relation": "rationale_for", "confidence": "EXTRACTED", "source_file": "client.py", "source_location": "L71", "weight": 1.0}]}